genqo/__init__.py
genqo/genqo.py
genqo-0.1.1.dist-info/METADATA
genqo-0.1.1.dist-info/WHEEL
genqo-0.1.1.dist-info/licenses/LICENSE
genqo-0.1.1.dist-info/RECORD
