Metadata-Version: 2.4
Name: genqo
Version: 0.1.1
Summary: A hybrid gaussian/non-gaussian quantum optics state engine
Project-URL: Homepage, https://github.com/jgr-rgb/genqo
Project-URL: Issues, https://github.com/jgr-rgb/genqo/issues
Author-email: Gabriel Richardson <rgb@umd.com>
License-Expression: MIT
License-File: LICENSE
Classifier: Operating System :: OS Independent
Classifier: Programming Language :: Python :: 3
Requires-Python: >=3.9
Requires-Dist: hickle
Requires-Dist: joblib
Requires-Dist: matplotlib
Requires-Dist: numba
Requires-Dist: numpy
Requires-Dist: pandas
Requires-Dist: scipy
Requires-Dist: sympy
Requires-Dist: thewalrus
Requires-Dist: tqdm
